yapf_isort/__init__.py
yapf_isort/__main__.py
yapf_isort/py.typed
yapf_isort/quotes.py
yapf_isort-0.7.0.dist-info/LICENSE
yapf_isort-0.7.0.dist-info/METADATA
yapf_isort-0.7.0.dist-info/WHEEL
yapf_isort-0.7.0.dist-info/entry_points.txt
yapf_isort-0.7.0.dist-info/RECORD
