Metadata-Version: 2.1
Name: yapf-isort
Version: 0.7.0
Summary: yapf 💌 isort
Author-email: Dominic Davis-Foster <dominic@davis-foster.co.uk>
License: Apache-2.0
Home-page: https://github.com/domdfcoding/yapf-isort
Project-URL: Issue Tracker, https://github.com/domdfcoding/yapf-isort/issues
Project-URL: Source Code, https://github.com/domdfcoding/yapf-isort
Platform: Windows
Platform: macOS
Platform: Linux
Classifier: License :: OSI Approved :: Apache Software License
Classifier: Operating System :: OS Independent
Classifier: Programming Language :: Python
Classifier: Programming Language :: Python :: 3 :: Only
Classifier: Programming Language :: Python :: 3.6
Classifier: Programming Language :: Python :: 3.7
Classifier: Programming Language :: Python :: 3.8
Classifier: Programming Language :: Python :: 3.9
Classifier: Programming Language :: Python :: 3.10
Classifier: Programming Language :: Python :: 3.11
Classifier: Programming Language :: Python :: 3.12
Classifier: Programming Language :: Python :: Implementation :: CPython
Classifier: Typing :: Typed
Requires-Python: >=3.6
Requires-Dist: click>=7.1.2
Requires-Dist: consolekit>=0.3.0
Requires-Dist: domdf-python-tools>=0.10.0
Requires-Dist: formate>=0.7.0
